samppy/__init__.py
samppy/credibility.py
samppy/credibility_pd.py
samppy/hamiltonian_sampler.py
samppy/sample_entropy.py
samppy-1.3.1.dist-info/LICENSE.txt
samppy-1.3.1.dist-info/METADATA
samppy-1.3.1.dist-info/WHEEL
samppy-1.3.1.dist-info/top_level.txt
samppy-1.3.1.dist-info/RECORD
