Metadata-Version: 2.2
Name: samppy
Version: 1.3.1
Summary: Hamiltonian sampling and analysis of sampled distributions
Author: Arne Leijon
Author-email: leijon@kth.se
License: MIT License
Keywords: sampling,Hamiltonian,MCMC,Bayesian,credibility,entropy
Classifier: Programming Language :: Python :: 3.10
Classifier: License :: OSI Approved :: MIT License
Classifier: Operating System :: OS Independent
Classifier: Intended Audience :: Science/Research
Classifier: Topic :: Scientific/Engineering :: Information Analysis
Requires-Python: >=3.10
License-File: LICENSE.txt
Requires-Dist: numpy>=2.2
Requires-Dist: scipy
